README.md
setup.cfg
setup.py
custom_format/__init__.py
custom_format/formatter.py
custom_format/generator_html.py
custom_format.egg-info/PKG-INFO
custom_format.egg-info/SOURCES.txt
custom_format.egg-info/dependency_links.txt
custom_format.egg-info/requires.txt
custom_format.egg-info/top_level.txt